{"nodes": [{"id": "c_users_efeha_documents_eslesbulusapp_components_story_storyprogressbar_tsx", "label": "StoryProgressBar.tsx", "file_type": "code", "source_file": "C:\\Users\\efeha\\Documents\\eslesbulusapp\\components\\story\\StoryProgressBar.tsx", "source_location": "L1"}, {"id": "story_storyprogressbar_props", "label": "Props", "file_type": "code", "source_file": "C:\\Users\\efeha\\Documents\\eslesbulusapp\\components\\story\\StoryProgressBar.tsx", "source_location": "L8"}, {"id": "story_storyprogressbar_storyprogressbar", "label": "StoryProgressBar()", "file_type": "code", "source_file": "C:\\Users\\efeha\\Documents\\eslesbulusapp\\components\\story\\StoryProgressBar.tsx", "source_location": "L14"}, {"id": "story_storyprogressbar_segment", "label": "Segment()", "file_type": "code", "source_file": "C:\\Users\\efeha\\Documents\\eslesbulusapp\\components\\story\\StoryProgressBar.tsx", "source_location": "L24"}, {"id": "story_storyprogressbar_styles", "label": "styles", "file_type": "code", "source_file": "C:\\Users\\efeha\\Documents\\eslesbulusapp\\components\\story\\StoryProgressBar.tsx", "source_location": "L47"}], "edges": [{"source": "c_users_efeha_documents_eslesbulusapp_components_story_storyprogressbar_tsx", "target": "react_native", "relation": "imports_from", "context": "import", "confidence": "EXTRACTED", "source_file": "C:\\Users\\efeha\\Documents\\eslesbulusapp\\components\\story\\StoryProgressBar.tsx", "source_location": "L1", "weight": 1.0}, {"source": "c_users_efeha_documents_eslesbulusapp_components_story_storyprogressbar_tsx", "target": "react_native_reanimated", "relation": "imports_from", "context": "import", "confidence": "EXTRACTED", "source_file": "C:\\Users\\efeha\\Documents\\eslesbulusapp\\components\\story\\StoryProgressBar.tsx", "source_location": "L2", "weight": 1.0}, {"source": "c_users_efeha_documents_eslesbulusapp_components_story_storyprogressbar_tsx", "target": "story_storyprogressbar_props", "relation": "contains", "confidence": "EXTRACTED", "source_file": "C:\\Users\\efeha\\Documents\\eslesbulusapp\\components\\story\\StoryProgressBar.tsx", "source_location": "L8", "weight": 1.0}, {"source": "c_users_efeha_documents_eslesbulusapp_components_story_storyprogressbar_tsx", "target": "story_storyprogressbar_storyprogressbar", "relation": "contains", "confidence": "EXTRACTED", "source_file": "C:\\Users\\efeha\\Documents\\eslesbulusapp\\components\\story\\StoryProgressBar.tsx", "source_location": "L14", "weight": 1.0}, {"source": "c_users_efeha_documents_eslesbulusapp_components_story_storyprogressbar_tsx", "target": "story_storyprogressbar_segment", "relation": "contains", "confidence": "EXTRACTED", "source_file": "C:\\Users\\efeha\\Documents\\eslesbulusapp\\components\\story\\StoryProgressBar.tsx", "source_location": "L24", "weight": 1.0}, {"source": "c_users_efeha_documents_eslesbulusapp_components_story_storyprogressbar_tsx", "target": "story_storyprogressbar_styles", "relation": "contains", "confidence": "EXTRACTED", "source_file": "C:\\Users\\efeha\\Documents\\eslesbulusapp\\components\\story\\StoryProgressBar.tsx", "source_location": "L47", "weight": 1.0}], "raw_calls": [{"caller_nid": "story_storyprogressbar_storyprogressbar", "callee": "map", "is_member_call": true, "source_file": "C:\\Users\\efeha\\Documents\\eslesbulusapp\\components\\story\\StoryProgressBar.tsx", "source_location": "L17"}, {"caller_nid": "story_storyprogressbar_storyprogressbar", "callee": "from", "is_member_call": true, "source_file": "C:\\Users\\efeha\\Documents\\eslesbulusapp\\components\\story\\StoryProgressBar.tsx", "source_location": "L17"}, {"caller_nid": "story_storyprogressbar_segment", "callee": "useAnimatedStyle", "is_member_call": false, "source_file": "C:\\Users\\efeha\\Documents\\eslesbulusapp\\components\\story\\StoryProgressBar.tsx", "source_location": "L33"}]}