{"nodes": [{"id": "c_users_efeha_documents_eslesbulusapp_hooks_useusers_ts", "label": "useUsers.ts", "file_type": "code", "source_file": "C:\\Users\\efeha\\Documents\\eslesbulusapp\\hooks\\useUsers.ts", "source_location": "L1"}, {"id": "hooks_useusers_useusers", "label": "useUsers()", "file_type": "code", "source_file": "C:\\Users\\efeha\\Documents\\eslesbulusapp\\hooks\\useUsers.ts", "source_location": "L14"}], "edges": [{"source": "c_users_efeha_documents_eslesbulusapp_hooks_useusers_ts", "target": "react", "relation": "imports_from", "context": "import", "confidence": "EXTRACTED", "source_file": "C:\\Users\\efeha\\Documents\\eslesbulusapp\\hooks\\useUsers.ts", "source_location": "L1", "weight": 1.0}, {"source": "c_users_efeha_documents_eslesbulusapp_hooks_useusers_ts", "target": "firestore", "relation": "imports_from", "context": "import", "confidence": "EXTRACTED", "source_file": "C:\\Users\\efeha\\Documents\\eslesbulusapp\\hooks\\useUsers.ts", "source_location": "L2", "weight": 1.0}, {"source": "c_users_efeha_documents_eslesbulusapp_hooks_useusers_ts", "target": "c_users_efeha_documents_eslesbulusapp_config_firebase_ts", "relation": "imports_from", "context": "import", "confidence": "EXTRACTED", "source_file": "C:\\Users\\efeha\\Documents\\eslesbulusapp\\hooks\\useUsers.ts", "source_location": "L3", "weight": 1.0}, {"source": "c_users_efeha_documents_eslesbulusapp_hooks_useusers_ts", "target": "config_firebase_db", "relation": "imports", "context": "import", "confidence": "EXTRACTED", "source_file": "C:\\Users\\efeha\\Documents\\eslesbulusapp\\hooks\\useUsers.ts", "source_location": "L3", "weight": 1.0}, {"source": "c_users_efeha_documents_eslesbulusapp_hooks_useusers_ts", "target": "c_users_efeha_documents_eslesbulusapp_context_authcontext_tsx", "relation": "imports_from", "context": "import", "confidence": "EXTRACTED", "source_file": "C:\\Users\\efeha\\Documents\\eslesbulusapp\\hooks\\useUsers.ts", "source_location": "L4", "weight": 1.0}, {"source": "c_users_efeha_documents_eslesbulusapp_hooks_useusers_ts", "target": "context_authcontext_useauth", "relation": "imports", "context": "import", "confidence": "EXTRACTED", "source_file": "C:\\Users\\efeha\\Documents\\eslesbulusapp\\hooks\\useUsers.ts", "source_location": "L4", "weight": 1.0}, {"source": "c_users_efeha_documents_eslesbulusapp_hooks_useusers_ts", "target": "c_users_efeha_documents_eslesbulusapp_context_authcontext_tsx", "relation": "imports_from", "context": "import", "confidence": "EXTRACTED", "source_file": "C:\\Users\\efeha\\Documents\\eslesbulusapp\\hooks\\useUsers.ts", "source_location": "L5", "weight": 1.0}, {"source": "c_users_efeha_documents_eslesbulusapp_hooks_useusers_ts", "target": "context_authcontext_userprofile", "relation": "imports", "context": "import", "confidence": "EXTRACTED", "source_file": "C:\\Users\\efeha\\Documents\\eslesbulusapp\\hooks\\useUsers.ts", "source_location": "L5", "weight": 1.0}, {"source": "c_users_efeha_documents_eslesbulusapp_hooks_useusers_ts", "target": "c_users_efeha_documents_eslesbulusapp_constants_filters_ts", "relation": "imports_from", "context": "import", "confidence": "EXTRACTED", "source_file": "C:\\Users\\efeha\\Documents\\eslesbulusapp\\hooks\\useUsers.ts", "source_location": "L6", "weight": 1.0}, {"source": "c_users_efeha_documents_eslesbulusapp_hooks_useusers_ts", "target": "constants_filters_applyfilters", "relation": "imports", "context": "import", "confidence": "EXTRACTED", "source_file": "C:\\Users\\efeha\\Documents\\eslesbulusapp\\hooks\\useUsers.ts", "source_location": "L6", "weight": 1.0}, {"source": "c_users_efeha_documents_eslesbulusapp_hooks_useusers_ts", "target": "constants_filters_filters", "relation": "imports", "context": "import", "confidence": "EXTRACTED", "source_file": "C:\\Users\\efeha\\Documents\\eslesbulusapp\\hooks\\useUsers.ts", "source_location": "L6", "weight": 1.0}, {"source": "c_users_efeha_documents_eslesbulusapp_hooks_useusers_ts", "target": "hooks_useusers_useusers", "relation": "contains", "confidence": "EXTRACTED", "source_file": "C:\\Users\\efeha\\Documents\\eslesbulusapp\\hooks\\useUsers.ts", "source_location": "L14", "weight": 1.0}], "raw_calls": [{"caller_nid": "hooks_useusers_useusers", "callee": "useAuth", "is_member_call": false, "source_file": "C:\\Users\\efeha\\Documents\\eslesbulusapp\\hooks\\useUsers.ts", "source_location": "L19"}, {"caller_nid": "hooks_useusers_useusers", "callee": "useState", "is_member_call": false, "source_file": "C:\\Users\\efeha\\Documents\\eslesbulusapp\\hooks\\useUsers.ts", "source_location": "L20"}, {"caller_nid": "hooks_useusers_useusers", "callee": "useState", "is_member_call": false, "source_file": "C:\\Users\\efeha\\Documents\\eslesbulusapp\\hooks\\useUsers.ts", "source_location": "L21"}, {"caller_nid": "hooks_useusers_useusers", "callee": "useState", "is_member_call": false, "source_file": "C:\\Users\\efeha\\Documents\\eslesbulusapp\\hooks\\useUsers.ts", "source_location": "L22"}, {"caller_nid": "hooks_useusers_useusers", "callee": "useEffect", "is_member_call": false, "source_file": "C:\\Users\\efeha\\Documents\\eslesbulusapp\\hooks\\useUsers.ts", "source_location": "L24"}, {"caller_nid": "hooks_useusers_useusers", "callee": "applyFilters", "is_member_call": false, "source_file": "C:\\Users\\efeha\\Documents\\eslesbulusapp\\hooks\\useUsers.ts", "source_location": "L46"}]}